LICENSE
MANIFEST.in
README.md
setup.py
tox.ini
boto3facade/__init__.py
boto3facade/aws.py
boto3facade/boto3facade.ini
boto3facade/cloudformation.py
boto3facade/config.py
boto3facade/dynamodb.py
boto3facade/ec2.py
boto3facade/exceptions.py
boto3facade/iam.py
boto3facade/kinesis.py
boto3facade/kms.py
boto3facade/redshift.py
boto3facade/s3.py
boto3facade/utils.py
boto3facade.egg-info/PKG-INFO
boto3facade.egg-info/SOURCES.txt
boto3facade.egg-info/dependency_links.txt
boto3facade.egg-info/requires.txt
boto3facade.egg-info/top_level.txt
tests/__init__.py
tests/conftest.py
tests/test_aws.py
tests/test_cloudformation.py
tests/test_config.py
tests/test_ec2.py
tests/test_iam.py
tests/test_redshift.py
tests/test_s3.py