Metadata-Version: 1.1
Name: boto3facade
Version: 0.5.7
Summary: A simple facade for Boto3
Home-page: http://github.com/findhotel/boto3facade
Author: German Gomez Herrero, FindHotel BV
Author-email: data@findhotel.net
License: MIT
Platform: UNKNOWN
Classifier: Programming Language :: Python :: 2
Classifier: Programming Language :: Python :: 3
